tests/test_cattp.py
tests/__init__.py
cattp/__init__.py
cattp/http.py
cattp-0.0.2.dist-info/RECORD
cattp-0.0.2.dist-info/metadata.json
cattp-0.0.2.dist-info/WHEEL
cattp-0.0.2.dist-info/DESCRIPTION.rst
cattp-0.0.2.dist-info/top_level.txt
cattp-0.0.2.dist-info/METADATA
