Metadata-Version: 2.0
Name: cattp
Version: 0.0.2
Summary: Django responses with cats from https://http.cat
Home-page: https://github.com/lotrekagency/cattp
Author: Lotrek
Author-email: dimmitutto@lotrek.it
License: MIT
Platform: UNKNOWN
Classifier: Environment :: Web Environment
Classifier: Framework :: Django
Classifier: Intended Audience :: Developers
Classifier: Programming Language :: Python
Classifier: Programming Language :: Python :: 3
